firestream/__init__.py
firestream/firestream.py
firestream/api/__init__.py
firestream/api/api.py
firestream/layers/__init__.py
firestream/layers/attention_layer.py
firestream/model/__init__.py
firestream/model/disaggregator.py
firestream/model/window_gru.py
firestream/model/window_lstm.py
firestream/model/window_lstm_gru.py
firestream/model/you_net.py
firestream/runner/__init__.py
firestream/runner/runner.py
firestream/stream/__init__.py
firestream/stream/callbacks.py
firestream/stream/input.py
firestream/tpu/__init__.py
firestream/tpu/tpu.py
firestream/tpu/runner/__init__.py
firestream/tpu/runner/runner.py
firestream/tpu/stream/__init__.py
firestream/tpu/stream/callbacks.py
firestream/tpu/stream/input.py
firestream-0.0.27.dist-info/LICENSE
firestream-0.0.27.dist-info/METADATA
firestream-0.0.27.dist-info/WHEEL
firestream-0.0.27.dist-info/top_level.txt
firestream-0.0.27.dist-info/RECORD
