Metadata-Version: 2.1
Name: firestream
Version: 0.0.27
Summary: Deep learning package for automating experimentation, prototyping and tuning
Home-page: https://asimbluemoon@bitbucket.org/laylaelectric/ml.git
Author: Mohammad Asim
Author-email: asim.98.12.26@gmail.com
License: LICENSE.txt
Keywords: python,firestream
Platform: UNKNOWN
Classifier: Development Status :: 1 - Planning
Classifier: Programming Language :: Python :: 3
Classifier: Operating System :: OS Independent
License-File: LICENSE
Requires-Dist: tensorflow (>=2.1)
